{"mean":{"confidence_interval":{"confidence_level":0.95,"lower_bound":311405.2641611937,"upper_bound":314589.4006868933},"point_estimate":313073.20452182164,"standard_error":806.5075260851468},"median":{"confidence_interval":{"confidence_level":0.95,"lower_bound":313656.2923728814,"upper_bound":315914.2987012987},"point_estimate":315185.033771107,"standard_error":630.1141601591983},"median_abs_dev":{"confidence_interval":{"confidence_level":0.95,"lower_bound":3878.6246432239946,"upper_bound":6295.838338540063},"point_estimate":4946.233359082998,"standard_error":617.9090544715514},"slope":{"confidence_interval":{"confidence_level":0.95,"lower_bound":314928.47475171724,"upper_bound":316459.05839108024},"point_estimate":315718.8772144229,"standard_error":390.50891379630843},"std_dev":{"confidence_interval":{"confidence_level":0.95,"lower_bound":5767.330607593126,"upper_bound":10071.495404367699},"point_estimate":8084.086738390658,"standard_error":1103.1682698176096}}