{"mean":{"confidence_interval":{"confidence_level":0.95,"lower_bound":310995.138584163,"upper_bound":323795.8189572515},"point_estimate":316547.8817239955,"standard_error":3339.1599634906374},"median":{"confidence_interval":{"confidence_level":0.95,"lower_bound":309227.9368131868,"upper_bound":309368.7642857143},"point_estimate":309291.36158536584,"standard_error":34.19793872691545},"median_abs_dev":{"confidence_interval":{"confidence_level":0.95,"lower_bound":186.06092310262403,"upper_bound":411.334855798193},"point_estimate":262.7403561527229,"standard_error":59.96147127348971},"slope":{"confidence_interval":{"confidence_level":0.95,"lower_bound":309323.8759164935,"upper_bound":309726.79072569805},"point_estimate":309503.14110462536,"standard_error":103.86848045987864},"std_dev":{"confidence_interval":{"confidence_level":0.95,"lower_bound":12016.360729127064,"upper_bound":47767.888648865424},"point_estimate":33511.328203554825,"standard_error":9156.274477108038}}