{"mean":{"confidence_interval":{"confidence_level":0.95,"lower_bound":376760.6802139521,"upper_bound":377748.05581509694},"point_estimate":377379.011778122,"standard_error":271.4912143046322},"median":{"confidence_interval":{"confidence_level":0.95,"lower_bound":377601.8527131783,"upper_bound":377751.2735042735},"point_estimate":377675.5548245614,"standard_error":36.40292808254326},"median_abs_dev":{"confidence_interval":{"confidence_level":0.95,"lower_bound":280.9886986659012,"upper_bound":461.48944191401904},"point_estimate":350.14101490138,"standard_error":47.084274591172715},"slope":{"confidence_interval":{"confidence_level":0.95,"lower_bound":377436.87345307117,"upper_bound":377774.0567440245},"point_estimate":377616.56797202106,"standard_error":86.09643496467135},"std_dev":{"confidence_interval":{"confidence_level":0.95,"lower_bound":508.39925431933506,"upper_bound":4557.699908690459},"point_estimate":2714.6831073230305,"standard_error":1349.0971133412481}}