{"mean":{"confidence_interval":{"confidence_level":0.95,"lower_bound":57453937.62275,"upper_bound":57807870.58},"point_estimate":57637874.36,"standard_error":90572.61250152664},"median":{"confidence_interval":{"confidence_level":0.95,"lower_bound":57401461.0,"upper_bound":57804173.0},"point_estimate":57575496.0,"standard_error":90518.42545820924},"median_abs_dev":{"confidence_interval":{"confidence_level":0.95,"lower_bound":487220.89895009995,"upper_bound":758545.5897331238},"point_estimate":606230.681437254,"standard_error":67166.80649672404},"slope":null,"std_dev":{"confidence_interval":{"confidence_level":0.95,"lower_bound":597920.6932578696,"upper_bound":1254620.157173022},"point_estimate":913380.544811577,"standard_error":176920.23676562574}}