{"mean":{"confidence_interval":{"confidence_level":0.95,"lower_bound":18229333.592666663,"upper_bound":18364858.404833343},"point_estimate":18283108.44333333,"standard_error":36733.33564313406},"median":{"confidence_interval":{"confidence_level":0.95,"lower_bound":18222388.666666668,"upper_bound":18229005.333333336},"point_estimate":18224955.333333336,"standard_error":1667.4273156624718},"median_abs_dev":{"confidence_interval":{"confidence_level":0.95,"lower_bound":7561.259865760803,"upper_bound":14579.146841168404},"point_estimate":10872.646906971931,"standard_error":1777.577320684343},"slope":null,"std_dev":{"confidence_interval":{"confidence_level":0.95,"lower_bound":17825.49272691148,"upper_bound":582100.6190740052},"point_estimate":367282.50709936995,"standard_error":155153.27443935783}}