{"mean":{"confidence_interval":{"confidence_level":0.95,"lower_bound":6491529.672375,"upper_bound":6497006.61},"point_estimate":6493924.315,"standard_error":1407.3494498953082},"median":{"confidence_interval":{"confidence_level":0.95,"lower_bound":6490102.4375,"upper_bound":6491308.25},"point_estimate":6490794.375,"standard_error":325.7534085481111},"median_abs_dev":{"confidence_interval":{"confidence_level":0.95,"lower_bound":2071.2848257273436,"upper_bound":4055.8375529944897},"point_estimate":3146.2624691426754,"standard_error":506.8952151051027},"slope":null,"std_dev":{"confidence_interval":{"confidence_level":0.95,"lower_bound":4249.115825971016,"upper_bound":20685.745126449587},"point_estimate":14148.672503387237,"standard_error":4006.078113384994}}