{"mean":{"confidence_interval":{"confidence_level":0.95,"lower_bound":18073880.483416673,"upper_bound":18102779.88433334},"point_estimate":18088275.19,"standard_error":7385.553134437865},"median":{"confidence_interval":{"confidence_level":0.95,"lower_bound":18066375.666666668,"upper_bound":18105825.666666664},"point_estimate":18087108.833333336,"standard_error":9770.038421182917},"median_abs_dev":{"confidence_interval":{"confidence_level":0.95,"lower_bound":59649.691841005355,"upper_bound":100742.66821146019},"point_estimate":78207.14861154556,"standard_error":10925.453111040364},"slope":null,"std_dev":{"confidence_interval":{"confidence_level":0.95,"lower_bound":63999.989044663685,"upper_bound":83495.28775961472},"point_estimate":74094.86969096691,"standard_error":4992.783751220325}}