{"mean":{"confidence_interval":{"confidence_level":0.95,"lower_bound":52726.17461623828,"upper_bound":52804.65661184063},"point_estimate":52764.4008104393,"standard_error":20.035735065483614},"median":{"confidence_interval":{"confidence_level":0.95,"lower_bound":52698.85523143684,"upper_bound":52782.68661971831},"point_estimate":52742.37813527961,"standard_error":23.160751422921564},"median_abs_dev":{"confidence_interval":{"confidence_level":0.95,"lower_bound":130.79521857175646,"upper_bound":217.63991736417157},"point_estimate":181.9303590984511,"standard_error":22.92365413112732},"slope":{"confidence_interval":{"confidence_level":0.95,"lower_bound":52791.58709441669,"upper_bound":52860.557352119},"point_estimate":52825.674941628495,"standard_error":17.594134229282915},"std_dev":{"confidence_interval":{"confidence_level":0.95,"lower_bound":161.17742057332723,"upper_bound":237.0959966985156},"point_estimate":201.21730532829122,"standard_error":19.500506344464483}}