{"mean":{"confidence_interval":{"confidence_level":0.95,"lower_bound":55945.5732589049,"upper_bound":56174.17721123545},"point_estimate":56050.70154197986,"standard_error":58.415554913375246},"median":{"confidence_interval":{"confidence_level":0.95,"lower_bound":55835.12637362637,"upper_bound":55923.0324005891},"point_estimate":55894.29215367965,"standard_error":21.153789324096433},"median_abs_dev":{"confidence_interval":{"confidence_level":0.95,"lower_bound":125.62552052256262,"upper_bound":205.59324777856028},"point_estimate":163.11262692873302,"standard_error":19.919482333844236},"slope":{"confidence_interval":{"confidence_level":0.95,"lower_bound":55937.83078734676,"upper_bound":56146.5557117418},"point_estimate":56030.73860795035,"standard_error":53.8510532497339},"std_dev":{"confidence_interval":{"confidence_level":0.95,"lower_bound":355.8322354731966,"upper_bound":787.8895905650835},"point_estimate":588.8630228525666,"standard_error":110.71646444036725}}