{"mean":{"confidence_interval":{"confidence_level":0.95,"lower_bound":68056.95034789895,"upper_bound":69227.06709670193},"point_estimate":68621.40169694346,"standard_error":299.0908683976101},"median":{"confidence_interval":{"confidence_level":0.95,"lower_bound":67594.69323671497,"upper_bound":68805.74518999518},"point_estimate":68314.25156118143,"standard_error":343.2458692190626},"median_abs_dev":{"confidence_interval":{"confidence_level":0.95,"lower_bound":1651.5381889674857,"upper_bound":2744.630593465651},"point_estimate":2266.5603527697617,"standard_error":278.3166678867511},"slope":{"confidence_interval":{"confidence_level":0.95,"lower_bound":68313.56050736002,"upper_bound":69576.19466244132},"point_estimate":68902.65184079602,"standard_error":321.7187062419861},"std_dev":{"confidence_interval":{"confidence_level":0.95,"lower_bound":2303.239908861671,"upper_bound":3768.187489477608},"point_estimate":3011.659779651245,"standard_error":381.8654122504173}}