{"mean":{"confidence_interval":{"confidence_level":0.95,"lower_bound":8417.523563926605,"upper_bound":8555.424949169494},"point_estimate":8470.286727845638,"standard_error":37.57455560099365},"median":{"confidence_interval":{"confidence_level":0.95,"lower_bound":8444.743498688811,"upper_bound":8459.855846774193},"point_estimate":8453.458815982405,"standard_error":3.4062619244249426},"median_abs_dev":{"confidence_interval":{"confidence_level":0.95,"lower_bound":28.59763557649322,"upper_bound":57.11363748184897},"point_estimate":38.39352425319049,"standard_error":7.2537605053837115},"slope":{"confidence_interval":{"confidence_level":0.95,"lower_bound":8449.221592927666,"upper_bound":8480.004292297155},"point_estimate":8462.833857322299,"standard_error":7.921344372294299},"std_dev":{"confidence_interval":{"confidence_level":0.95,"lower_bound":87.0668268083165,"upper_bound":633.988170152537},"point_estimate":378.16891991118035,"standard_error":184.13471816452497}}