{"mean":{"confidence_interval":{"confidence_level":0.95,"lower_bound":6678.5449133147995,"upper_bound":6704.496796001833},"point_estimate":6691.1828737141095,"standard_error":6.615341724187346},"median":{"confidence_interval":{"confidence_level":0.95,"lower_bound":6672.097402597403,"upper_bound":6698.80177187154},"point_estimate":6687.12520661157,"standard_error":7.202918799107067},"median_abs_dev":{"confidence_interval":{"confidence_level":0.95,"lower_bound":35.82286238054569,"upper_bound":62.67823366616153},"point_estimate":48.096932087652604,"standard_error":6.9492871373476435},"slope":{"confidence_interval":{"confidence_level":0.95,"lower_bound":6676.667346306761,"upper_bound":6710.668173253761},"point_estimate":6693.071853782393,"standard_error":8.650821131618342},"std_dev":{"confidence_interval":{"confidence_level":0.95,"lower_bound":52.12082590613574,"upper_bound":79.06275272792055},"point_estimate":66.39071524938139,"standard_error":6.891961429636333}}