{"mean":{"confidence_interval":{"confidence_level":0.95,"lower_bound":9068.75553562866,"upper_bound":9215.924780779307},"point_estimate":9134.196646659484,"standard_error":37.72739450180803},"median":{"confidence_interval":{"confidence_level":0.95,"lower_bound":8948.30827067669,"upper_bound":9218.21590909091},"point_estimate":9087.550487012986,"standard_error":82.81573956874239},"median_abs_dev":{"confidence_interval":{"confidence_level":0.95,"lower_bound":153.03487120653134,"upper_bound":397.43863053545545},"point_estimate":277.682693175507,"standard_error":66.59508048058188},"slope":{"confidence_interval":{"confidence_level":0.95,"lower_bound":9089.535117147367,"upper_bound":9322.371076389121},"point_estimate":9182.559780236019,"standard_error":63.2479763669407},"std_dev":{"confidence_interval":{"confidence_level":0.95,"lower_bound":222.2009958122087,"upper_bound":561.4235549169847},"point_estimate":379.0186731536717,"standard_error":107.0887832021131}}