{"mean":{"confidence_interval":{"confidence_level":0.95,"lower_bound":2726193.4755131584,"upper_bound":2739376.506039473},"point_estimate":2732031.805263158,"standard_error":3402.7140094381607},"median":{"confidence_interval":{"confidence_level":0.95,"lower_bound":2721890.5263157897,"upper_bound":2725198.4736842103},"point_estimate":2723351.052631579,"standard_error":745.955868847767},"median_abs_dev":{"confidence_interval":{"confidence_level":0.95,"lower_bound":5595.020174352837,"upper_bound":8798.333480639989},"point_estimate":6941.0648872977445,"standard_error":783.0588277209457},"slope":null,"std_dev":{"confidence_interval":{"confidence_level":0.95,"lower_bound":15011.979444296296,"upper_bound":50619.932663409025},"point_estimate":34275.02138472874,"standard_error":9283.904674915382}}