{"mean":{"confidence_interval":{"confidence_level":0.95,"lower_bound":6902.803372146699,"upper_bound":6993.802683704479},"point_estimate":6938.67449553026,"standard_error":23.99539300236356},"median":{"confidence_interval":{"confidence_level":0.95,"lower_bound":6890.233026123335,"upper_bound":6906.857261628343},"point_estimate":6896.525587044534,"standard_error":4.152558914273571},"median_abs_dev":{"confidence_interval":{"confidence_level":0.95,"lower_bound":29.467590681794245,"upper_bound":54.86719922231131},"point_estimate":41.104484150234526,"standard_error":6.72220839906266},"slope":{"confidence_interval":{"confidence_level":0.95,"lower_bound":6911.718927778285,"upper_bound":6969.657241439929},"point_estimate":6936.959178820293,"standard_error":14.931652529000493},"std_dev":{"confidence_interval":{"confidence_level":0.95,"lower_bound":62.74299329341395,"upper_bound":392.3380384604605},"point_estimate":239.7261616817486,"standard_error":102.3844550248773}}