{"mean":{"confidence_interval":{"confidence_level":0.95,"lower_bound":3717405.2485535718,"upper_bound":3740212.9857678576},"point_estimate":3726415.9235714283,"standard_error":6031.149164844439},"median":{"confidence_interval":{"confidence_level":0.95,"lower_bound":3708322.714285714,"upper_bound":3720841.214285714},"point_estimate":3714944.8571428573,"standard_error":3377.4938165491226},"median_abs_dev":{"confidence_interval":{"confidence_level":0.95,"lower_bound":13954.283902261544,"upper_bound":26291.951383224656},"point_estimate":19044.84386188668,"standard_error":3178.394218402889},"slope":null,"std_dev":{"confidence_interval":{"confidence_level":0.95,"lower_bound":20243.088358731533,"upper_bound":98801.12925068632},"point_estimate":60494.52456935517,"standard_error":26363.981026544163}}