{"mean":{"confidence_interval":{"confidence_level":0.95,"lower_bound":9539.663816297341,"upper_bound":9706.604504100069},"point_estimate":9622.860051783877,"standard_error":42.723434784494046},"median":{"confidence_interval":{"confidence_level":0.95,"lower_bound":9463.504545454545,"upper_bound":9719.850399305556},"point_estimate":9579.21130952381,"standard_error":68.93277042422595},"median_abs_dev":{"confidence_interval":{"confidence_level":0.95,"lower_bound":341.6157439351073,"upper_bound":523.523991061016},"point_estimate":427.28976021409096,"standard_error":47.96086009590484},"slope":{"confidence_interval":{"confidence_level":0.95,"lower_bound":9764.618386687622,"upper_bound":9977.258440069318},"point_estimate":9869.926060883701,"standard_error":54.024255309348895},"std_dev":{"confidence_interval":{"confidence_level":0.95,"lower_bound":361.30861672870395,"upper_bound":501.85909483587375},"point_estimate":430.88025179394185,"standard_error":36.047010191656156}}