{"mean":{"confidence_interval":{"confidence_level":0.95,"lower_bound":6526080.84803125,"upper_bound":6551470.56753125},"point_estimate":6536603.035,"standard_error":6615.946643044936},"median":{"confidence_interval":{"confidence_level":0.95,"lower_bound":6520379.25,"upper_bound":6523468.25},"point_estimate":6521302.375,"standard_error":738.1636495979278},"median_abs_dev":{"confidence_interval":{"confidence_level":0.95,"lower_bound":4971.1577117443085,"upper_bound":8889.206129685044},"point_estimate":7079.692861810327,"standard_error":937.030387780081},"slope":null,"std_dev":{"confidence_interval":{"confidence_level":0.95,"lower_bound":18875.917279677262,"upper_bound":105882.47579229652},"point_estimate":66517.493215601,"standard_error":24634.663988558656}}