{"mean":{"confidence_interval":{"confidence_level":0.95,"lower_bound":16503916.787250001,"upper_bound":16524182.47000001},"point_estimate":16512682.943333337,"standard_error":5189.821841729545},"median":{"confidence_interval":{"confidence_level":0.95,"lower_bound":16500711.166666668,"upper_bound":16503361.5},"point_estimate":16502044.5,"standard_error":747.2941136940607},"median_abs_dev":{"confidence_interval":{"confidence_level":0.95,"lower_bound":4200.205725431442,"upper_bound":7019.12247538386},"point_estimate":5584.707000851171,"standard_error":685.0239047666382},"slope":null,"std_dev":{"confidence_interval":{"confidence_level":0.95,"lower_bound":10911.006154679788,"upper_bound":78473.92032416357},"point_estimate":52491.50263640958,"standard_error":16788.411865702303}}