{"mean":{"confidence_interval":{"confidence_level":0.95,"lower_bound":6542441.6733125,"upper_bound":6608116.29284375},"point_estimate":6571351.77125,"standard_error":16922.44735567344},"median":{"confidence_interval":{"confidence_level":0.95,"lower_bound":6515152.4375,"upper_bound":6517752.4375},"point_estimate":6516520.0,"standard_error":639.0062188477269},"median_abs_dev":{"confidence_interval":{"confidence_level":0.95,"lower_bound":4342.164672911167,"upper_bound":8893.65392960608},"point_estimate":6462.097310274839,"standard_error":1201.4603778087837},"slope":null,"std_dev":{"confidence_interval":{"confidence_level":0.95,"lower_bound":74004.89626663686,"upper_bound":252398.9079060917},"point_estimate":169937.00681553726,"standard_error":46861.49593166237}}