{"mean":{"confidence_interval":{"confidence_level":0.95,"lower_bound":26896746.71775,"upper_bound":27161947.28},"point_estimate":27034801.66,"standard_error":67600.17730453987},"median":{"confidence_interval":{"confidence_level":0.95,"lower_bound":26974281.5,"upper_bound":27477046.25},"point_estimate":27162886.75,"standard_error":143201.38224880723},"median_abs_dev":{"confidence_interval":{"confidence_level":0.95,"lower_bound":414345.9211438894,"upper_bound":770060.573078692},"point_estimate":532399.4266480207,"standard_error":101819.21061069392},"slope":null,"std_dev":{"confidence_interval":{"confidence_level":0.95,"lower_bound":524396.2131202861,"upper_bound":844227.6676342092},"point_estimate":676661.9725631587,"standard_error":84437.7387190369}}