{"mean":{"confidence_interval":{"confidence_level":0.95,"lower_bound":7083835.253250001,"upper_bound":7122606.456785714},"point_estimate":7102547.94,"standard_error":9902.065211954816},"median":{"confidence_interval":{"confidence_level":0.95,"lower_bound":7053458.857142857,"upper_bound":7092973.428571428},"point_estimate":7075987.428571428,"standard_error":11549.77638969385},"median_abs_dev":{"confidence_interval":{"confidence_level":0.95,"lower_bound":51975.930877242376,"upper_bound":99504.27363344641},"point_estimate":76650.63043917909,"standard_error":12490.711797103853},"slope":null,"std_dev":{"confidence_interval":{"confidence_level":0.95,"lower_bound":77589.64182960392,"upper_bound":123336.11681143857},"point_estimate":99672.81385140674,"standard_error":11944.419480973378}}