{"mean":{"confidence_interval":{"confidence_level":0.95,"lower_bound":8598415.451000001,"upper_bound":8628056.94375},"point_estimate":8613322.701666668,"standard_error":7559.387460927083},"median":{"confidence_interval":{"confidence_level":0.95,"lower_bound":8593666.25,"upper_bound":8627435.333333334},"point_estimate":8618315.583333332,"standard_error":9360.599997212597},"median_abs_dev":{"confidence_interval":{"confidence_level":0.95,"lower_bound":48282.350742816925,"upper_bound":79126.58298522102},"point_estimate":64275.033108890515,"standard_error":7847.482109035643},"slope":null,"std_dev":{"confidence_interval":{"confidence_level":0.95,"lower_bound":60712.63739816885,"upper_bound":90693.6893618971},"point_estimate":75985.5151209308,"standard_error":7721.914649138628}}