{"mean":{"confidence_interval":{"confidence_level":0.95,"lower_bound":30825078.1595,"upper_bound":31592242.227625},"point_estimate":31215879.135,"standard_error":196147.1151094732},"median":{"confidence_interval":{"confidence_level":0.95,"lower_bound":30992801.0,"upper_bound":32197895.0},"point_estimate":31671928.25,"standard_error":300915.3156745405},"median_abs_dev":{"confidence_interval":{"confidence_level":0.95,"lower_bound":1322401.7106726766,"upper_bound":2147669.1176712513},"point_estimate":1638561.7072597146,"standard_error":204244.14812161712},"slope":null,"std_dev":{"confidence_interval":{"confidence_level":0.95,"lower_bound":1609386.166248053,"upper_bound":2308292.2289616913},"point_estimate":1979022.0614713808,"standard_error":178452.35440796296}}