{"mean":{"confidence_interval":{"confidence_level":0.95,"lower_bound":98367.42653909567,"upper_bound":99163.30049436691},"point_estimate":98696.52291910295,"standard_error":207.25882736795145},"median":{"confidence_interval":{"confidence_level":0.95,"lower_bound":98193.93902439025,"upper_bound":98935.29814814814},"point_estimate":98697.69097222222,"standard_error":193.90625656112053},"median_abs_dev":{"confidence_interval":{"confidence_level":0.95,"lower_bound":881.1395766643416,"upper_bound":1420.470883566184},"point_estimate":1190.257221612973,"standard_error":135.11161496266143},"slope":{"confidence_interval":{"confidence_level":0.95,"lower_bound":97741.9023730819,"upper_bound":99733.54246841265},"point_estimate":98433.59379439437,"standard_error":562.0531919779952},"std_dev":{"confidence_interval":{"confidence_level":0.95,"lower_bound":888.9350611687365,"upper_bound":3346.619380577444},"point_estimate":2092.2976551115735,"standard_error":818.8618877923611}}