{"mean":{"confidence_interval":{"confidence_level":0.95,"lower_bound":97269.94192887862,"upper_bound":97558.79133624356},"point_estimate":97408.4628478576,"standard_error":73.86010147990028},"median":{"confidence_interval":{"confidence_level":0.95,"lower_bound":97195.3803986711,"upper_bound":97497.78571428571},"point_estimate":97348.45035542306,"standard_error":80.15740025911357},"median_abs_dev":{"confidence_interval":{"confidence_level":0.95,"lower_bound":457.18359773020967,"upper_bound":734.942424063954},"point_estimate":588.9451895441276,"standard_error":69.00284171956947},"slope":{"confidence_interval":{"confidence_level":0.95,"lower_bound":97082.98808950305,"upper_bound":97369.47594978429},"point_estimate":97216.22321856066,"standard_error":72.90496975463331},"std_dev":{"confidence_interval":{"confidence_level":0.95,"lower_bound":545.6188265003293,"upper_bound":967.2556476154358},"point_estimate":741.0048392563659,"standard_error":114.37584124896539}}