{"mean":{"confidence_interval":{"confidence_level":0.95,"lower_bound":93372.23606803917,"upper_bound":95133.01965383186},"point_estimate":94376.1603674572,"standard_error":454.3658987668592},"median":{"confidence_interval":{"confidence_level":0.95,"lower_bound":95121.99119417169,"upper_bound":95396.49740259741},"point_estimate":95273.57287355501,"standard_error":72.62105290580882},"median_abs_dev":{"confidence_interval":{"confidence_level":0.95,"lower_bound":407.327110303538,"upper_bound":963.5444879299041},"point_estimate":613.3406051848131,"standard_error":145.23799865810264},"slope":{"confidence_interval":{"confidence_level":0.95,"lower_bound":95606.52067833865,"upper_bound":96089.041579973},"point_estimate":95833.35929497427,"standard_error":123.52191069266034},"std_dev":{"confidence_interval":{"confidence_level":0.95,"lower_bound":1790.7246765020584,"upper_bound":7022.692331231666},"point_estimate":4557.622766948581,"standard_error":1462.8326441433949}}