{"mean":{"confidence_interval":{"confidence_level":0.95,"lower_bound":93828.73842246403,"upper_bound":95005.54890613163},"point_estimate":94433.23952181984,"standard_error":301.08198121211404},"median":{"confidence_interval":{"confidence_level":0.95,"lower_bound":95299.3990332244,"upper_bound":95829.05082417582},"point_estimate":95648.7261537064,"standard_error":136.5996915417626},"median_abs_dev":{"confidence_interval":{"confidence_level":0.95,"lower_bound":779.1561536075089,"upper_bound":1476.6373433496572},"point_estimate":1085.316380536741,"standard_error":181.49212880928368},"slope":{"confidence_interval":{"confidence_level":0.95,"lower_bound":94912.79888850603,"upper_bound":95963.682090502},"point_estimate":95455.39384291414,"standard_error":265.7115258480438},"std_dev":{"confidence_interval":{"confidence_level":0.95,"lower_bound":2504.412796736043,"upper_bound":3438.969576914715},"point_estimate":3026.351560024631,"standard_error":238.27440517437037}}