{"mean":{"confidence_interval":{"confidence_level":0.95,"lower_bound":32389476.20475,"upper_bound":32431460.367999997},"point_estimate":32410229.82,"standard_error":10730.049754616377},"median":{"confidence_interval":{"confidence_level":0.95,"lower_bound":32371732.75,"upper_bound":32426532.25},"point_estimate":32403382.5,"standard_error":15053.405626190204},"median_abs_dev":{"confidence_interval":{"confidence_level":0.95,"lower_bound":83151.24887377024,"upper_bound":134708.66295844316},"point_estimate":99296.39193713665,"standard_error":12988.919616639787},"slope":null,"std_dev":{"confidence_interval":{"confidence_level":0.95,"lower_bound":91570.20312144319,"upper_bound":123083.13844964505},"point_estimate":107947.5668991294,"standard_error":8051.098002713038}}