{"mean":{"confidence_interval":{"confidence_level":0.95,"lower_bound":76222.07361033245,"upper_bound":77448.74267052127},"point_estimate":76913.62201775011,"standard_error":317.5564034119031},"median":{"confidence_interval":{"confidence_level":0.95,"lower_bound":77544.96703296703,"upper_bound":77924.67944283977},"point_estimate":77828.36202594398,"standard_error":93.77305994490203},"median_abs_dev":{"confidence_interval":{"confidence_level":0.95,"lower_bound":393.3806783251019,"upper_bound":830.9486126591532},"point_estimate":584.5221897447113,"standard_error":101.81044918511789},"slope":{"confidence_interval":{"confidence_level":0.95,"lower_bound":77782.7973526359,"upper_bound":78122.45283151141},"point_estimate":77951.17684623341,"standard_error":86.13585178999246},"std_dev":{"confidence_interval":{"confidence_level":0.95,"lower_bound":1346.2786244071121,"upper_bound":4830.932818692008},"point_estimate":3191.492193982378,"standard_error":943.8262881749384}}