{"mean":{"confidence_interval":{"confidence_level":0.95,"lower_bound":76095423.03,"upper_bound":76430477.12475},"point_estimate":76261299.03,"standard_error":86055.40537091742},"median":{"confidence_interval":{"confidence_level":0.95,"lower_bound":76063630.0,"upper_bound":76410528.0},"point_estimate":76216761.0,"standard_error":87091.03326785802},"median_abs_dev":{"confidence_interval":{"confidence_level":0.95,"lower_bound":636303.7393033504,"upper_bound":1033462.6202523708},"point_estimate":900448.1984138489,"standard_error":106780.85655746562},"slope":null,"std_dev":{"confidence_interval":{"confidence_level":0.95,"lower_bound":717656.1582708316,"upper_bound":1006862.1302472207},"point_estimate":866486.5697807048,"standard_error":73881.75627509391}}