{"mean":{"confidence_interval":{"confidence_level":0.95,"lower_bound":76774.81076107187,"upper_bound":77319.9832082947},"point_estimate":77035.09832869963,"standard_error":139.0670863852716},"median":{"confidence_interval":{"confidence_level":0.95,"lower_bound":76219.1205479452,"upper_bound":76488.25185520362},"point_estimate":76321.45303880319,"standard_error":112.18330939969965},"median_abs_dev":{"confidence_interval":{"confidence_level":0.95,"lower_bound":388.1438633917805,"upper_bound":1203.805176268038},"point_estimate":689.6780235436316,"standard_error":219.7695286137016},"slope":{"confidence_interval":{"confidence_level":0.95,"lower_bound":76275.60586402516,"upper_bound":76585.0705710731},"point_estimate":76415.19129067534,"standard_error":79.32406051741417},"std_dev":{"confidence_interval":{"confidence_level":0.95,"lower_bound":1100.245219141603,"upper_bound":1772.3495056445377},"point_estimate":1402.9186007576886,"standard_error":191.5464685845301}}