{"mean":{"confidence_interval":{"confidence_level":0.95,"lower_bound":183223106.19125,"upper_bound":185646894.97599998},"point_estimate":184403196.35,"standard_error":619927.8484359712},"median":{"confidence_interval":{"confidence_level":0.95,"lower_bound":181677806.0,"upper_bound":184585273.0},"point_estimate":182926689.5,"standard_error":852235.1398162163},"median_abs_dev":{"confidence_interval":{"confidence_level":0.95,"lower_bound":3936420.796814561,"upper_bound":6671625.751554966},"point_estimate":4927593.735417724,"standard_error":712459.4928724493},"slope":null,"std_dev":{"confidence_interval":{"confidence_level":0.95,"lower_bound":5130452.406040499,"upper_bound":7222292.518317432},"point_estimate":6226851.9334089905,"standard_error":534427.8563124146}}