{"mean":{"confidence_interval":{"confidence_level":0.95,"lower_bound":119185680.3045,"upper_bound":119788338.17950001},"point_estimate":119481085.39,"standard_error":154083.51251701935},"median":{"confidence_interval":{"confidence_level":0.95,"lower_bound":118855668.0,"upper_bound":119669028.0},"point_estimate":119126718.5,"standard_error":196209.3510142802},"median_abs_dev":{"confidence_interval":{"confidence_level":0.95,"lower_bound":1211520.6531912088,"upper_bound":1820636.4741772413},"point_estimate":1546640.8795416355,"standard_error":159140.34061739733},"slope":null,"std_dev":{"confidence_interval":{"confidence_level":0.95,"lower_bound":1285770.697736447,"upper_bound":1790345.1733274865},"point_estimate":1545569.02084185,"standard_error":129326.32110656131}}