{"mean":{"confidence_interval":{"confidence_level":0.95,"lower_bound":9939756.935600001,"upper_bound":9952577.467550004},"point_estimate":9946037.461999997,"standard_error":3266.218564829035},"median":{"confidence_interval":{"confidence_level":0.95,"lower_bound":9933231.6,"upper_bound":9947647.2},"point_estimate":9940422.5,"standard_error":3553.9796968906426},"median_abs_dev":{"confidence_interval":{"confidence_level":0.95,"lower_bound":22283.774124384203,"upper_bound":39942.15508988501},"point_estimate":29364.0785586845,"standard_error":4360.786865168494},"slope":null,"std_dev":{"confidence_interval":{"confidence_level":0.95,"lower_bound":28174.09688986375,"upper_bound":36804.85383427234},"point_estimate":32812.42754113716,"standard_error":2204.368721751656}}