{"mean":{"confidence_interval":{"confidence_level":0.95,"lower_bound":9268220.862041663,"upper_bound":9289164.934208335},"point_estimate":9278666.941666668,"standard_error":5334.808374352561},"median":{"confidence_interval":{"confidence_level":0.95,"lower_bound":9253966.5,"upper_bound":9295399.5},"point_estimate":9267302.75,"standard_error":9089.39950094553},"median_abs_dev":{"confidence_interval":{"confidence_level":0.95,"lower_bound":39058.10790657951,"upper_bound":69446.95956707092},"point_estimate":58216.26476645424,"standard_error":7251.081857409821},"slope":null,"std_dev":{"confidence_interval":{"confidence_level":0.95,"lower_bound":46263.256866499374,"upper_bound":59765.9084664001},"point_estimate":53140.846370380365,"standard_error":3453.7568945285107}}