{"mean":{"confidence_interval":{"confidence_level":0.95,"lower_bound":11126244.3163,"upper_bound":11158501.757100008},"point_estimate":11142740.68,"standard_error":8248.556652951078},"median":{"confidence_interval":{"confidence_level":0.95,"lower_bound":11141976.8,"upper_bound":11181977.0},"point_estimate":11161627.0,"standard_error":9769.424174126838},"median_abs_dev":{"confidence_interval":{"confidence_level":0.95,"lower_bound":51713.38360190281,"upper_bound":99453.10275435337},"point_estimate":70512.75126814732,"standard_error":12886.268965300607},"slope":null,"std_dev":{"confidence_interval":{"confidence_level":0.95,"lower_bound":71385.31042377981,"upper_bound":93307.76953861892},"point_estimate":83128.17911178122,"standard_error":5605.629597687049}}