{"mean":{"confidence_interval":{"confidence_level":0.95,"lower_bound":19536267.355583336,"upper_bound":19541579.52233334},"point_estimate":19538600.976666667,"standard_error":1370.2834057801676},"median":{"confidence_interval":{"confidence_level":0.95,"lower_bound":19534027.0,"upper_bound":19537027.666666668},"point_estimate":19535541.5,"standard_error":897.1450404712458},"median_abs_dev":{"confidence_interval":{"confidence_level":0.95,"lower_bound":3957.3064297456076,"upper_bound":6724.826380611386},"point_estimate":5288.187006114073,"standard_error":716.8631738578072},"slope":null,"std_dev":{"confidence_interval":{"confidence_level":0.95,"lower_bound":6235.9199016621415,"upper_bound":20822.380839657253},"point_estimate":13810.700926668082,"standard_error":4011.2962963189316}}