{"mean":{"confidence_interval":{"confidence_level":0.95,"lower_bound":81877.34129483892,"upper_bound":82028.66951892669},"point_estimate":81953.26677751169,"standard_error":38.54581087929908},"median":{"confidence_interval":{"confidence_level":0.95,"lower_bound":81938.91666666667,"upper_bound":82045.2418128655},"point_estimate":82012.4909090909,"standard_error":33.16245068130953},"median_abs_dev":{"confidence_interval":{"confidence_level":0.95,"lower_bound":263.02015203243127,"upper_bound":450.1555872798758},"point_estimate":370.6893491636283,"standard_error":47.61902020334784},"slope":{"confidence_interval":{"confidence_level":0.95,"lower_bound":82058.51712112721,"upper_bound":82213.6700904253},"point_estimate":82137.48134062362,"standard_error":39.5189221878068},"std_dev":{"confidence_interval":{"confidence_level":0.95,"lower_bound":333.0387681127158,"upper_bound":440.83365328353403},"point_estimate":388.4515788429806,"standard_error":27.597704245139067}}