{"mean":{"confidence_interval":{"confidence_level":0.95,"lower_bound":79411.89007701863,"upper_bound":79563.5879792151},"point_estimate":79485.28826736557,"standard_error":38.71718229188255},"median":{"confidence_interval":{"confidence_level":0.95,"lower_bound":79431.3826121795,"upper_bound":79522.42342342342},"point_estimate":79462.22677119629,"standard_error":23.8423757825808},"median_abs_dev":{"confidence_interval":{"confidence_level":0.95,"lower_bound":177.62346984670037,"upper_bound":332.18740444880797},"point_estimate":235.61236148017244,"standard_error":39.44861980335937},"slope":{"confidence_interval":{"confidence_level":0.95,"lower_bound":79537.50595902928,"upper_bound":79676.47900576118},"point_estimate":79603.55712427958,"standard_error":35.57368223867184},"std_dev":{"confidence_interval":{"confidence_level":0.95,"lower_bound":279.02464246461403,"upper_bound":499.0327589133033},"point_estimate":389.47102801459937,"standard_error":56.934621332891304}}