{"mean":{"confidence_interval":{"confidence_level":0.95,"lower_bound":8087171.784535711,"upper_bound":8142799.783214284},"point_estimate":8114637.925714283,"standard_error":14142.891836950967},"median":{"confidence_interval":{"confidence_level":0.95,"lower_bound":8082708.0,"upper_bound":8154237.428571428},"point_estimate":8125668.857142857,"standard_error":18091.110801398514},"median_abs_dev":{"confidence_interval":{"confidence_level":0.95,"lower_bound":103479.86546286555,"upper_bound":190129.78552452184},"point_estimate":149034.76175410397,"standard_error":21425.675398365805},"slope":null,"std_dev":{"confidence_interval":{"confidence_level":0.95,"lower_bound":120244.4259486482,"upper_bound":163972.65598922383},"point_estimate":141675.664836282,"standard_error":11297.535290242413}}