{"mean":{"confidence_interval":{"confidence_level":0.95,"lower_bound":114955294.70799999,"upper_bound":115558621.95324999},"point_estimate":115249329.84,"standard_error":153452.5346876667},"median":{"confidence_interval":{"confidence_level":0.95,"lower_bound":114721524.0,"upper_bound":115305867.0},"point_estimate":115016815.0,"standard_error":156810.82986696545},"median_abs_dev":{"confidence_interval":{"confidence_level":0.95,"lower_bound":909206.3241733615,"upper_bound":1477242.5986737013},"point_estimate":1171071.6194093227,"standard_error":141198.52448908085},"slope":null,"std_dev":{"confidence_interval":{"confidence_level":0.95,"lower_bound":1206031.9425615137,"upper_bound":1867732.0036834888},"point_estimate":1550269.9657866869,"standard_error":169816.3319858259}}