{"mean":{"confidence_interval":{"confidence_level":0.95,"lower_bound":276848.88944745564,"upper_bound":277117.87764076574},"point_estimate":276983.2905965698,"standard_error":68.451781995291},"median":{"confidence_interval":{"confidence_level":0.95,"lower_bound":276815.44715447153,"upper_bound":277073.81333333335},"point_estimate":276992.8141025641,"standard_error":62.55169422863705},"median_abs_dev":{"confidence_interval":{"confidence_level":0.95,"lower_bound":410.17448806204635,"upper_bound":702.3898243559204},"point_estimate":546.6872661277229,"standard_error":72.72620202300567},"slope":{"confidence_interval":{"confidence_level":0.95,"lower_bound":276937.95336791914,"upper_bound":277152.5555178195},"point_estimate":277046.95498448354,"standard_error":54.65247429587228},"std_dev":{"confidence_interval":{"confidence_level":0.95,"lower_bound":539.9259174796541,"upper_bound":835.1288592136309},"point_estimate":688.2813628670791,"standard_error":75.96770802760877}}