{"mean":{"confidence_interval":{"confidence_level":0.95,"lower_bound":52721.37719980451,"upper_bound":52838.72241146838},"point_estimate":52775.33323278409,"standard_error":29.93815727401136},"median":{"confidence_interval":{"confidence_level":0.95,"lower_bound":52654.566287878784,"upper_bound":52762.9375},"point_estimate":52714.21443208431,"standard_error":27.862540527365567},"median_abs_dev":{"confidence_interval":{"confidence_level":0.95,"lower_bound":128.23944698800184,"upper_bound":190.09690945843897},"point_estimate":165.88382541434623,"standard_error":15.799379212316733},"slope":{"confidence_interval":{"confidence_level":0.95,"lower_bound":52784.54779658937,"upper_bound":52952.90913262657},"point_estimate":52862.245424855915,"standard_error":43.324520621828206},"std_dev":{"confidence_interval":{"confidence_level":0.95,"lower_bound":187.33009839875285,"upper_bound":398.925242249784},"point_estimate":300.22785776899934,"standard_error":54.142927243355516}}