{"mean":{"confidence_interval":{"confidence_level":0.95,"lower_bound":105212.88607061683,"upper_bound":105627.3103230531},"point_estimate":105419.038373234,"standard_error":105.30340108348021},"median":{"confidence_interval":{"confidence_level":0.95,"lower_bound":105347.2456043956,"upper_bound":105590.86230636833},"point_estimate":105488.25552606178,"standard_error":58.513228033188},"median_abs_dev":{"confidence_interval":{"confidence_level":0.95,"lower_bound":407.8123820129336,"upper_bound":723.8355164003588},"point_estimate":537.5401358042719,"standard_error":82.31583116897663},"slope":{"confidence_interval":{"confidence_level":0.95,"lower_bound":105342.6776874603,"upper_bound":105623.72182640906},"point_estimate":105472.68409339442,"standard_error":71.39814033855647},"std_dev":{"confidence_interval":{"confidence_level":0.95,"lower_bound":766.5996495450593,"upper_bound":1347.3116308081608},"point_estimate":1057.7193597031228,"standard_error":149.71346560496139}}