{"mean":{"confidence_interval":{"confidence_level":0.95,"lower_bound":2360678.428625,"upper_bound":2361729.5822045463},"point_estimate":2361174.0281818183,"standard_error":268.81459485382004},"median":{"confidence_interval":{"confidence_level":0.95,"lower_bound":2360372.8863636367,"upper_bound":2361727.4318181816},"point_estimate":2361007.0,"standard_error":315.13516956601734},"median_abs_dev":{"confidence_interval":{"confidence_level":0.95,"lower_bound":1738.685423677304,"upper_bound":2571.030527082168},"point_estimate":2170.020929656371,"standard_error":218.68773551235256},"slope":null,"std_dev":{"confidence_interval":{"confidence_level":0.95,"lower_bound":1805.5518664562564,"upper_bound":3585.21950109067},"point_estimate":2689.3627890081307,"standard_error":467.5118806840467}}