{"mean":{"confidence_interval":{"confidence_level":0.95,"lower_bound":14684998.607687501,"upper_bound":14762485.4996875},"point_estimate":14722052.21,"standard_error":19774.57295116626},"median":{"confidence_interval":{"confidence_level":0.95,"lower_bound":14626893.25,"upper_bound":14641993.25},"point_estimate":14635571.875,"standard_error":4181.085152360199},"median_abs_dev":{"confidence_interval":{"confidence_level":0.95,"lower_bound":15641.615047305822,"upper_bound":33649.83030259609},"point_estimate":23326.857335865498,"standard_error":4792.865015295455},"slope":null,"std_dev":{"confidence_interval":{"confidence_level":0.95,"lower_bound":154746.60741367357,"upper_bound":230546.23931936783},"point_estimate":197935.31785346175,"standard_error":19340.191709144427}}