{"mean":{"confidence_interval":{"confidence_level":0.95,"lower_bound":7788354.944607141,"upper_bound":7838919.117142859},"point_estimate":7811869.235714287,"standard_error":12911.014896179002},"median":{"confidence_interval":{"confidence_level":0.95,"lower_bound":7776063.285714285,"upper_bound":7815685.214285715},"point_estimate":7800702.214285715,"standard_error":10455.163513789705},"median_abs_dev":{"confidence_interval":{"confidence_level":0.95,"lower_bound":76368.54461418856,"upper_bound":134738.8974079062},"point_estimate":99587.40513197111,"standard_error":14762.247861794685},"slope":null,"std_dev":{"confidence_interval":{"confidence_level":0.95,"lower_bound":85253.26430260767,"upper_bound":178990.93687358926},"point_estimate":128932.16405899666,"standard_error":26724.54681964081}}