{"mean":{"confidence_interval":{"confidence_level":0.95,"lower_bound":8790.984922482992,"upper_bound":8802.399392348323},"point_estimate":8796.371281217656,"standard_error":2.9238552914286764},"median":{"confidence_interval":{"confidence_level":0.95,"lower_bound":8784.097100200976,"upper_bound":8798.03149001536},"point_estimate":8790.786484852713,"standard_error":3.9956513177980946},"median_abs_dev":{"confidence_interval":{"confidence_level":0.95,"lower_bound":18.478110153443225,"upper_bound":31.102869605207676},"point_estimate":26.051863133966496,"standard_error":3.391557254228515},"slope":{"confidence_interval":{"confidence_level":0.95,"lower_bound":8792.916725000918,"upper_bound":8803.211380289129},"point_estimate":8798.006020064693,"standard_error":2.623507827178344},"std_dev":{"confidence_interval":{"confidence_level":0.95,"lower_bound":20.863915624223008,"upper_bound":38.863918319973465},"point_estimate":29.407880157883316,"standard_error":4.845550096600785}}