{"mean":{"confidence_interval":{"confidence_level":0.95,"lower_bound":6398.9693835266835,"upper_bound":6431.241604284329},"point_estimate":6412.35798438108,"standard_error":8.326341912418668},"median":{"confidence_interval":{"confidence_level":0.95,"lower_bound":6390.737878787879,"upper_bound":6404.549105924106},"point_estimate":6397.164743409326,"standard_error":3.6252198516876493},"median_abs_dev":{"confidence_interval":{"confidence_level":0.95,"lower_bound":28.717368487255683,"upper_bound":50.57212675689605},"point_estimate":39.162340782002076,"standard_error":5.856311496467972},"slope":{"confidence_interval":{"confidence_level":0.95,"lower_bound":6404.819186538273,"upper_bound":6425.893042861376},"point_estimate":6414.918336311243,"standard_error":5.395746699075466},"std_dev":{"confidence_interval":{"confidence_level":0.95,"lower_bound":33.75389064709546,"upper_bound":133.5546429962501},"point_estimate":83.89114268128355,"standard_error":31.62551504601358}}