{"mean":{"confidence_interval":{"confidence_level":0.95,"lower_bound":2933270.963205883,"upper_bound":3000379.494220587},"point_estimate":2964363.3164705904,"standard_error":17123.38464302777},"median":{"confidence_interval":{"confidence_level":0.95,"lower_bound":2925202.470588235,"upper_bound":2962252.676470588},"point_estimate":2947358.294117647,"standard_error":10323.537653006077},"median_abs_dev":{"confidence_interval":{"confidence_level":0.95,"lower_bound":85641.9950266094,"upper_bound":173952.7572176034},"point_estimate":121477.35211393435,"standard_error":23826.90575783244},"slope":null,"std_dev":{"confidence_interval":{"confidence_level":0.95,"lower_bound":113070.18521195874,"upper_bound":240066.46317501654},"point_estimate":172945.03691593272,"standard_error":35349.544011529}}